<QUICKQUOTE>
	<DWELLINGDETAILS ID="1" ADDRESS="" POLICYTYPE="DP-3" POLICYCODE="DP-2^REPLACE">
		<LOB_ID>6</LOB_ID>
		<POLICY_ID></POLICY_ID>
		<TERRITORYCODES></TERRITORYCODES>
		<INSURANCESCORE>100</INSURANCESCORE>
		<TERRITORYZONE></TERRITORYZONE>
		<TERRITORYNAME></TERRITORYNAME>
		<TERRITORYCOUNTY></TERRITORYCOUNTY>
		<EARTHQUAKEZONE></EARTHQUAKEZONE>
		<!--Basic Policy Page-->
		<STATENAME></STATENAME>
		<NEWBUSINESSFACTOR>Y</NEWBUSINESSFACTOR>
		<QUOTEEFFDATE></QUOTEEFFDATE>
		<QUOTEEXPDATE></QUOTEEXPDATE>
		<QQNUMBER></QQNUMBER>
		<TERMFACTOR>12</TERMFACTOR>
		<PRODUCTNAME>DP-3</PRODUCTNAME>
		<PRODUCT_PREMIER></PRODUCT_PREMIER>
		<SEASONALSECONDARY>N</SEASONALSECONDARY>
		<LOCATIONCODE>REN_LO1</LOCATIONCODE>
		<REPLACEMENTCOSTFACTOR>75000</REPLACEMENTCOSTFACTOR>
		<DWELLING_LIMITS>75000</DWELLING_LIMITS>
		<DEDUCTIBLE>500</DEDUCTIBLE>
		<FIREPROTECTIONCLASS>04</FIREPROTECTIONCLASS>
		<PROTECTIONCLASS>04</PROTECTIONCLASS>
		<DISTANCET_FIRESTATION>5</DISTANCET_FIRESTATION>
		<FEET2HYDRANT>1000 or less</FEET2HYDRANT>
		<EXTERIOR_CONSTRUCTION_DESC></EXTERIOR_CONSTRUCTION_DESC>
		<EXTERIOR_CONSTRUCTION>11298</EXTERIOR_CONSTRUCTION>
		<EXTERIOR_CONSTRUCTION_F_M>M</EXTERIOR_CONSTRUCTION_F_M>
		<DWELL_UND_CONSTRUCTION_DP1143>N</DWELL_UND_CONSTRUCTION_DP1143>
		<DOC>1974</DOC>
		<AGEOFHOME>31</AGEOFHOME>
		<NUMBEROFFAMILIES>1</NUMBEROFFAMILIES>
		<N0_LOCAL_ALARM>0</N0_LOCAL_ALARM>
		<NO_YEARS_WITH_WOLVERINE>0</NO_YEARS_WITH_WOLVERINE>
		<LOSSFREE>N</LOSSFREE>
		<MULTIPLEPOLICYFACTOR>N</MULTIPLEPOLICYFACTOR>
		<FORM_CODE></FORM_CODE>
		<COVERAGEVALUE>0.00</COVERAGEVALUE>
		<!--Optional Coverages Page-->
		<PERSONALLIABILITY_LIMIT>100000</PERSONALLIABILITY_LIMIT>
		<MEDICALPAYMENTSTOOTHERS_LIMIT>1000</MEDICALPAYMENTSTOOTHERS_LIMIT>
		<EARTHQUAKEDP469>N</EARTHQUAKEDP469>
		<INCIDENTALOFFICE>N</INCIDENTALOFFICE>
		<INCIDENTALOFFICE_SMALL_OFFICE>N</INCIDENTALOFFICE_SMALL_OFFICE>
		<MINESUBSIDENCEDP480>N</MINESUBSIDENCEDP480>
		<MINESUBSIDENCEDP480_DED></MINESUBSIDENCEDP480_DED>
		<MINESUBSIDENCEDP480_COVG_LIMIT></MINESUBSIDENCEDP480_COVG_LIMIT>
		<APPURTENANTSTRUCTURES_INCLUDE>7500</APPURTENANTSTRUCTURES_INCLUDE>
		<APPURTENANTSTRUCTURES_ADDITIONAL>0</APPURTENANTSTRUCTURES_ADDITIONAL>
		<BUILDINGIMPROVEMENTS_INCLUDE></BUILDINGIMPROVEMENTS_INCLUDE>
		<BUILDINGIMPROVEMENTS_ADDITIONAL>0</BUILDINGIMPROVEMENTS_ADDITIONAL>
		<RENTALVALUE_INCLUDE>7500</RENTALVALUE_INCLUDE>
		<RENTALVALUE_ADDITIONAL>0</RENTALVALUE_ADDITIONAL>
		<PERSONALPROPERTY_INCLUDE>3750</PERSONALPROPERTY_INCLUDE>
		<PERSONALPROPERTY_ADDITIONAL>0</PERSONALPROPERTY_ADDITIONAL>
		<CONTENTSINSTORAGE_INCLUDE></CONTENTSINSTORAGE_INCLUDE>
		<CONTENTSINSTORAGE_ADDITIONAL>0</CONTENTSINSTORAGE_ADDITIONAL>
		<TREESLAWNSSHRUBS_INCLUDE></TREESLAWNSSHRUBS_INCLUDE>
		<TREESLAWNSSHRUBS_ADDITIONAL>0</TREESLAWNSSHRUBS_ADDITIONAL>
		<RADIOTV_INCLUDE></RADIOTV_INCLUDE>
		<RADIOTV_ADDITIONAL>0</RADIOTV_ADDITIONAL>
		<SATELLITEDISHES_INCLUDE>500</SATELLITEDISHES_INCLUDE>
		<SATELLITEDISHES_ADDITIONAL>0</SATELLITEDISHES_ADDITIONAL>
		<AWNINGSCANOPIES_INCLUDE></AWNINGSCANOPIES_INCLUDE>
		<AWNINGSCANOPIES_ADDITIONAL>0</AWNINGSCANOPIES_ADDITIONAL>
		<FLOATERBUILDINGMATERIALS_INCLUDE></FLOATERBUILDINGMATERIALS_INCLUDE>
		<FLOATERBUILDINGMATERIALS_ADDITIONAL>0</FLOATERBUILDINGMATERIALS_ADDITIONAL>
		<FLOATERNONSTRUCTURAL_INCLUDE></FLOATERNONSTRUCTURAL_INCLUDE>
		<FLOATERNONSTRUCTURAL_ADDITIONAL>0</FLOATERNONSTRUCTURAL_ADDITIONAL>	
		<MINESUBSIDENCE_ADDITIONAL>0</MINESUBSIDENCE_ADDITIONAL>
		<OTHERSTRUCTURES>
			<PREMISES_LOCATION></PREMISES_LOCATION>
			<COVERAGE_BASIS></COVERAGE_BASIS>
			<ADDITIONAL_AMOUNT_OF_INSURANCE_DESIRED></ADDITIONAL_AMOUNT_OF_INSURANCE_DESIRED>
			<SATELLITE_EQUIPMENT></SATELLITE_EQUIPMENT>
		</OTHERSTRUCTURES>
	</DWELLINGDETAILS>
	<PRIMARYAPPLICANT></PRIMARYAPPLICANT>
</QUICKQUOTE>